uyishi132/__init__.py
uyishi134-0.0.1.dist-info/METADATA
uyishi134-0.0.1.dist-info/WHEEL
uyishi134-0.0.1.dist-info/top_level.txt
uyishi134-0.0.1.dist-info/RECORD
