Metadata-Version: 2.1
Name: uyishi134
Version: 0.0.1
Summary: Bu kutubxona ishlatilmaydi
Author: Sarvar
Author-email: sarvarsaydullayev185@gmail.com
